gomall/__init__.py
gomall/autolog/__init__.py
gomall/autolog/log.py
gomall/autolog/model.py
gomall-0.0.3.dist-info/LICENSE
gomall-0.0.3.dist-info/METADATA
gomall-0.0.3.dist-info/WHEEL
gomall-0.0.3.dist-info/top_level.txt
gomall-0.0.3.dist-info/RECORD
