Metadata-Version: 2.1
Name: gomall
Version: 0.0.3
Summary: 和gomall平台配合使用的python依赖包，包括实验追踪、指令构造、模型评估等工具
Author: GoMall Development Team
Author-email: wangwenshan@ict.ac.cn
Classifier: Programming Language :: Python :: 3
Classifier: License :: OSI Approved :: MIT License
Classifier: Operating System :: OS Independent
License-File: LICENSE
Requires-Dist: torch (<=2.00)
